alibabacloud_live20161101/__init__.py
alibabacloud_live20161101/client.py
alibabacloud_live20161101/models/__init__.py
alibabacloud_live20161101/models/_add_caster_component_request.py
alibabacloud_live20161101/models/_add_caster_component_response.py
alibabacloud_live20161101/models/_add_caster_component_response_body.py
alibabacloud_live20161101/models/_add_caster_episode_group_content_request.py
alibabacloud_live20161101/models/_add_caster_episode_group_content_response.py
alibabacloud_live20161101/models/_add_caster_episode_group_content_response_body.py
alibabacloud_live20161101/models/_add_caster_episode_group_request.py
alibabacloud_live20161101/models/_add_caster_episode_group_response.py
alibabacloud_live20161101/models/_add_caster_episode_group_response_body.py
alibabacloud_live20161101/models/_add_caster_episode_request.py
alibabacloud_live20161101/models/_add_caster_episode_response.py
alibabacloud_live20161101/models/_add_caster_episode_response_body.py
alibabacloud_live20161101/models/_add_caster_layout_request.py
alibabacloud_live20161101/models/_add_caster_layout_response.py
alibabacloud_live20161101/models/_add_caster_layout_response_body.py
alibabacloud_live20161101/models/_add_caster_program_request.py
alibabacloud_live20161101/models/_add_caster_program_response.py
alibabacloud_live20161101/models/_add_caster_program_response_body.py
alibabacloud_live20161101/models/_add_caster_video_resource_request.py
alibabacloud_live20161101/models/_add_caster_video_resource_response.py
alibabacloud_live20161101/models/_add_caster_video_resource_response_body.py
alibabacloud_live20161101/models/_add_custom_live_stream_transcode_request.py
alibabacloud_live20161101/models/_add_custom_live_stream_transcode_response.py
alibabacloud_live20161101/models/_add_custom_live_stream_transcode_response_body.py
alibabacloud_live20161101/models/_add_live_aiproduce_rules_request.py
alibabacloud_live20161101/models/_add_live_aiproduce_rules_response.py
alibabacloud_live20161101-2.6.0.dist-info/LICENSE
alibabacloud_live20161101-2.6.0.dist-info/METADATA
alibabacloud_live20161101-2.6.0.dist-info/WHEEL
alibabacloud_live20161101-2.6.0.dist-info/top_level.txt
alibabacloud_live20161101-2.6.0.dist-info/RECORD
